chem2dview/__init__.py
chem2dview/example.py
chem2dview/frontend/build/.DS_Store
chem2dview/frontend/build/bootstrap.min.css
chem2dview/frontend/build/index.html
chem2dview/frontend/build/assets/emotion-react-jsx-runtime.browser.esm-BDiFoFP9.js
chem2dview/frontend/build/assets/index-Dc9CkZGk.css
chem2dview/frontend/build/assets/index-xZiJ-BeD.js
chem2dview/frontend/build/assets/index.modern-D-tiaiIN.js
chem2dview/frontend/build/assets/index.modern-dffdbebd-CAjuhPPQ.js
streamlit_chem2dview-0.0.2.dist-info/licenses/LICENSE
streamlit_chem2dview-0.0.2.dist-info/METADATA
streamlit_chem2dview-0.0.2.dist-info/WHEEL
streamlit_chem2dview-0.0.2.dist-info/top_level.txt
streamlit_chem2dview-0.0.2.dist-info/RECORD
